envtoml/__init__.py
envtoml/py.typed
envtoml-0.3.1.dist-info/METADATA
envtoml-0.3.1.dist-info/WHEEL
envtoml-0.3.1.dist-info/licenses/LICENSE
envtoml-0.3.1.dist-info/RECORD
