Metadata-Version: 2.4
Name: envTOML
Version: 0.3.1
Summary: A simple way of using environment variables in TOML configs (via interpolation)
Project-URL: Repository, https://github.com/mrshu/envtoml
Author-email: "mr.Shu" <mr@shu.io>
License: MIT
License-File: LICENSE
Keywords: TOML,config,environment,variables
Classifier: Development Status :: 4 - Beta
Classifier: Intended Audience :: Developers
Classifier: License :: OSI Approved :: MIT License
Classifier: Programming Language :: Python :: 3
Classifier: Programming Language :: Python :: 3 :: Only
Classifier: Programming Language :: Python :: 3.8
Classifier: Programming Language :: Python :: 3.9
Classifier: Programming Language :: Python :: 3.10
Classifier: Programming Language :: Python :: 3.11
Classifier: Programming Language :: Python :: 3.12
Classifier: Programming Language :: Python :: 3.13
Classifier: Topic :: Software Development :: Libraries :: Python Modules
Requires-Python: >=3.8
Requires-Dist: tomli>=2.0; python_version < '3.11'
